{
  "model": "CardGridSection",
  "presets": [
    {
      "label": "Basic Card Grid",
      "thumbnail": "images/card-grid-section--basic.png",
      "data": {
        "heading": "Jump to Topic",
        "subheading": "Or jump right to a specific topic to help you build your site.\n",
        "cards": [
          {
            "heading": "How Stackbit Works →",
            "subheading": "Follow an end-to-end guide to learn the inner-workings of Stackbit.\n",
            "url": "https://docs.stackbit.com/conceptual-guides/how-stackbit-works/",
            "$$type": "Card"
          },
          {
            "heading": "Pages →",
            "subheading": "Add a new type of page to your site, while touching on content modeling and data retrieval.\n",
            "url": "https://docs.stackbit.com/how-to-guides/content/",
            "$$type": "Card"
          },
          {
            "heading": "Components →",
            "subheading": "Make components editable, add styles, and provide content presets to speed up content editing.\n",
            "url": "https://docs.stackbit.com/how-to-guides/components/",
            "$$type": "Card"
          },
          {
            "heading": "Styling →",
            "subheading": "Set up global styles and add a styling toolbar to individual components in the visual editor.\n",
            "url": "https://docs.stackbit.com/how-to-guides/styles/",
            "$$type": "Card"
          }
        ]
      }
    }
  ]
}
