{"objects":[{"__metadata":{"id":"content/pages/index.md","source":"sourcebit-source-filesystem","sourceName":"pages","sourcePath":"/Users/seancdavis/workspace/stackbit/examples/minimal/content/pages","relSourcePath":"index.md","relProjectPath":"content/pages/index.md","modelType":"page","modelName":"Page","modelLabel":"Page","urlPath":"/"},"frontmatter":{"title":"Hello World","body":"Velit sunt ea ipsum nostrud cupidatat ipsum ex Lorem."},"markdown":""},{"__metadata":{"id":"sourcebit-source-filesystem:data","source":"sourcebit-source-filesystem"}}],"props":{"liveUpdate":true,"liveUpdatePort":8088,"liveUpdateEventName":"props_changed"},"pages":[{"path":"/","__metadata":{"id":"content/pages/index.md","source":"sourcebit-source-filesystem","sourceName":"pages","sourcePath":"/Users/seancdavis/workspace/stackbit/examples/minimal/content/pages","relSourcePath":"index.md","relProjectPath":"content/pages/index.md","modelType":"page","modelName":"Page","modelLabel":"Page","urlPath":"/"},"frontmatter":{"title":"Hello World","body":"Velit sunt ea ipsum nostrud cupidatat ipsum ex Lorem."},"markdown":""}]}
